{
  "namespaces": [
    "public"
  ],
  "name": "public",
  "tables": [
    {
      "columns": {
        "id": {
          "name": "id",
          "type": "varchar(255)",
          "unsigned": false,
          "autoincrement": false,
          "primary": false,
          "nullable": false,
          "length": 255,
          "mappedType": "string"
        },
        "query": {
          "name": "query",
          "type": "varchar(255)",
          "unsigned": false,
          "autoincrement": false,
          "primary": false,
          "nullable": false,
          "length": 255,
          "mappedType": "string"
        },
        "timestamp": {
          "name": "timestamp",
          "type": "date",
          "unsigned": false,
          "autoincrement": false,
          "primary": false,
          "nullable": false,
          "length": 0,
          "mappedType": "date"
        },
        "count": {
          "name": "count",
          "type": "int",
          "unsigned": false,
          "autoincrement": false,
          "primary": false,
          "nullable": false,
          "default": "1",
          "mappedType": "integer"
        }
      },
      "name": "history",
      "schema": "public",
      "indexes": [
        {
          "keyName": "history_pkey",
          "columnNames": [
            "id"
          ],
          "composite": false,
          "constraint": true,
          "primary": true,
          "unique": true
        }
      ],
      "checks": [],
      "foreignKeys": {},
      "nativeEnums": {}
    }
  ],
  "nativeEnums": {}
}
